{"frame":618,"P1State":{"inputBuffer":[[],[],[["6","r"]],[],[["8","r"]],[],[],[],[],[],[],[]],"heldKeys":[],"unhandledInputs":[],"currentState":"Fall","frameCount":6,"stunRemaining":0,"health":100,"position":[235.56012,132.403336],"velocity":[200,-101],"facingRight":true,"touchingWall":false,"grounded":false,"combo":0},"P2State":{"inputBuffer":[[],[],[],[],[],[],[],[],[],[],[],[]],"heldKeys":["8"],"unhandledInputs":[],"currentState":"Jump","frameCount":10,"stunRemaining":0,"health":100,"position":[329.641144,200.837662],"velocity":[0,-322],"facingRight":false,"touchingWall":false,"grounded":false,"combo":0},"hitStopRemaining":0}